README.md
setup.cfg
setup.py
raisecom_netmiko/__init__.py
raisecom_netmiko/raisecom.py
raisecom_netmiko/utils.py
raisecom_netmiko.egg-info/PKG-INFO
raisecom_netmiko.egg-info/SOURCES.txt
raisecom_netmiko.egg-info/dependency_links.txt
raisecom_netmiko.egg-info/requires.txt
raisecom_netmiko.egg-info/top_level.txt