Metadata-Version: 2.1
Name: raisecom-netmiko
Version: 0.21
Summary: functionality for raisecom devices, via netmiko connection
Home-page: UNKNOWN
Author: Ilya Gulin
License: Apache 2.0
Platform: UNKNOWN
